{
  "formatVersion": 1,
  "database": {
    "version": 2,
    "identityHash": "50f2b869adc5cf70bf8469819f86d458",
    "entities": [
      {
        "tableName": "favorites",
        "createSql": "CREATE TABLE IF NOT EXISTS `${TABLE_NAME}` (`id` INTEGER PRIMARY KEY AUTOINCREMENT NOT NULL, `userId` TEXT, `itemId` TEXT, `itemType` TEXT, `title` TEXT, `location` TEXT, `imageUrl` TEXT, `price` REAL, `rating` REAL, `updatedAt` INTEGER)",
        "fields": [
          {
            "fieldPath": "id",
            "columnName": "id",
            "affinity": "INTEGER",
            "notNull": true
          },
          {
            "fieldPath": "userId",
            "columnName": "userId",
            "affinity": "TEXT",
            "notNull": false
          },
          {
            "fieldPath": "itemId",
            "columnName": "itemId",
            "affinity": "TEXT",
            "notNull": false
          },
          {
            "fieldPath": "itemType",
            "columnName": "itemType",
            "affinity": "TEXT",
            "notNull": false
          },
          {
            "fieldPath": "title",
            "columnName": "title",
            "affinity": "TEXT",
            "notNull": false
          },
          {
            "fieldPath": "location",
            "columnName": "location",
            "affinity": "TEXT",
            "notNull": false
          },
          {
            "fieldPath": "imageUrl",
            "columnName": "imageUrl",
            "affinity": "TEXT",
            "notNull": false
          },
          {
            "fieldPath": "price",
            "columnName": "price",
            "affinity": "REAL",
            "notNull": false
          },
          {
            "fieldPath": "rating",
            "columnName": "rating",
            "affinity": "REAL",
            "notNull": false
          },
          {
            "fieldPath": "updatedAt",
            "columnName": "updatedAt",
            "affinity": "INTEGER",
            "notNull": false
          }
        ],
        "primaryKey": {
          "autoGenerate": true,
          "columnNames": [
            "id"
          ]
        },
        "indices": [
          {
            "name": "index_favorites_userId_itemId_itemType",
            "unique": true,
            "columnNames": [
              "userId",
              "itemId",
              "itemType"
            ],
            "orders": [],
            "createSql": "CREATE UNIQUE INDEX IF NOT EXISTS `index_favorites_userId_itemId_itemType` ON `${TABLE_NAME}` (`userId`, `itemId`, `itemType`)"
          }
        ],
        "foreignKeys": []
      },
      {
        "tableName": "reservations",
        "createSql": "CREATE TABLE IF NOT EXISTS `${TABLE_NAME}` (`id` TEXT NOT NULL, `tourId` TEXT, `title` TEXT, `location` TEXT, `date` TEXT, `participants` TEXT, `price` REAL NOT NULL, `imageRes` INTEGER NOT NULL, `createdAt` INTEGER NOT NULL, PRIMARY KEY(`id`))",
        "fields": [
          {
            "fieldPath": "id",
            "columnName": "id",
            "affinity": "TEXT",
            "notNull": true
          },
          {
            "fieldPath": "tourId",
            "columnName": "tourId",
            "affinity": "TEXT",
            "notNull": false
          },
          {
            "fieldPath": "title",
            "columnName": "title",
            "affinity": "TEXT",
            "notNull": false
          },
          {
            "fieldPath": "location",
            "columnName": "location",
            "affinity": "TEXT",
            "notNull": false
          },
          {
            "fieldPath": "date",
            "columnName": "date",
            "affinity": "TEXT",
            "notNull": false
          },
          {
            "fieldPath": "participants",
            "columnName": "participants",
            "affinity": "TEXT",
            "notNull": false
          },
          {
            "fieldPath": "price",
            "columnName": "price",
            "affinity": "REAL",
            "notNull": true
          },
          {
            "fieldPath": "imageRes",
            "columnName": "imageRes",
            "affinity": "INTEGER",
            "notNull": true
          },
          {
            "fieldPath": "createdAt",
            "columnName": "createdAt",
            "affinity": "INTEGER",
            "notNull": true
          }
        ],
        "primaryKey": {
          "autoGenerate": false,
          "columnNames": [
            "id"
          ]
        },
        "indices": [],
        "foreignKeys": []
      }
    ],
    "views": [],
    "setupQueries": [
      "CREATE TABLE IF NOT EXISTS room_master_table (id INTEGER PRIMARY KEY,identity_hash TEXT)",
      "INSERT OR REPLACE INTO room_master_table (id,identity_hash) VALUES(42, '50f2b869adc5cf70bf8469819f86d458')"
    ]
  }
}